django3scaffold/__init__.py
django3scaffold/auth_backends.py
django3scaffold/classmaker.py
django3scaffold/context_processors.py
django3scaffold/db_fields.py
django3scaffold/decorators.py
django3scaffold/helper.py
django3scaffold/http.py
django3scaffold/middleware.py
django3scaffold/scaffold.py
django3scaffold/session.py
django3scaffold/settings.py
django3scaffold/tests.py
django3scaffold/tzinfo.py
django3scaffold/management/__init__.py
django3scaffold/management/commands/__init__.py
django3scaffold/management/commands/scaffold.py
django3scaffold/static/django_common/js/ajax_form.js
django3scaffold/static/django_common/js/common.js
django3scaffold/templates/common/fragments/form_field.html
django3scaffold/templates/common/fragments/radio_checkbox_field.html
django3scaffold/templatetags/__init__.py
django3scaffold/templatetags/custom_tags.py
django3scaffold-0.9.8.dist-info/AUTHORS
django3scaffold-0.9.8.dist-info/LICENSE
django3scaffold-0.9.8.dist-info/METADATA
django3scaffold-0.9.8.dist-info/WHEEL
django3scaffold-0.9.8.dist-info/top_level.txt
django3scaffold-0.9.8.dist-info/RECORD
