Metadata-Version: 2.1
Name: django3scaffold
Version: 0.9.8
Summary: Faster Development For Django 3 Projects
Home-page: https://github.com/tokyodevs/django3scaffold
Author: Tokyo Developers
Author-email: admin@tokyodevs.com
License: UNKNOWN
Keywords: django
Platform: UNKNOWN
Classifier: Framework :: Django
Classifier: Intended Audience :: Developers
Classifier: Intended Audience :: System Administrators
Classifier: Operating System :: OS Independent
Classifier: Topic :: Software Development
